custom_pyod/__init__.py
custom_pyod/utils.py
custom_pyod/models/__init__.py
custom_pyod/models/base.py
custom_pyod/models/copod.py
custom_pyod/models/ecod.py
custom_pyod-0.1.0.dist-info/METADATA
custom_pyod-0.1.0.dist-info/WHEEL
custom_pyod-0.1.0.dist-info/RECORD
